didl_lite/__init__.py
didl_lite/didl_lite.py
didl_lite/py.typed
didl_lite/utils.py
python_didl_lite-1.4.1.dist-info/LICENSE.md
python_didl_lite-1.4.1.dist-info/METADATA
python_didl_lite-1.4.1.dist-info/WHEEL
python_didl_lite-1.4.1.dist-info/top_level.txt
python_didl_lite-1.4.1.dist-info/RECORD
