Metadata-Version: 2.1
Name: python-didl-lite
Version: 1.4.1
Summary: DIDL-Lite (Digital Item Declaration Language) tools for Python
Home-page: https://github.com/StevenLooman/python-didl-lite
Author: Steven Looman
Author-email: steven.looman@gmail.com
Classifier: Development Status :: 5 - Production/Stable
Classifier: Intended Audience :: Developers
Classifier: License :: OSI Approved :: Apache Software License
Classifier: Programming Language :: Python
Classifier: Programming Language :: Python :: 3.8
Classifier: Programming Language :: Python :: 3.9
Classifier: Programming Language :: Python :: 3.10
Classifier: Programming Language :: Python :: 3.11
Classifier: Programming Language :: Python :: 3.12
Classifier: Programming Language :: Python :: 3.13
Requires-Python: >=3.8
License-File: LICENSE.md
Requires-Dist: defusedxml>=0.6.0
